CHANGELOG.md
CODE_OF_CONDUCT.md
CONTRIBUTING.md
LICENSE
MANIFEST.in
README.md
setup.cfg
setup.py
scripts/download_coco.sh
scripts/download_voc.sh
scripts/torchrayrc
torchray/VERSION
torchray/__init__.py
torchray/utils.py
torchray.egg-info/PKG-INFO
torchray.egg-info/SOURCES.txt
torchray.egg-info/dependency_links.txt
torchray.egg-info/requires.txt
torchray.egg-info/top_level.txt
torchray/attribution/__init__.py
torchray/attribution/common.py
torchray/attribution/deconvnet.py
torchray/attribution/excitation_backprop.py
torchray/attribution/extremal_perturbation.py
torchray/attribution/grad_cam.py
torchray/attribution/gradient.py
torchray/attribution/guided_backprop.py
torchray/attribution/linear_approx.py
torchray/attribution/rise.py
torchray/benchmark/__init__.py
torchray/benchmark/datasets.py
torchray/benchmark/imagenet_classes.txt
torchray/benchmark/logging.py
torchray/benchmark/models.py
torchray/benchmark/pointing_game.py
torchray/benchmark/pointing_game_ebp_coco_difficult.txt
torchray/benchmark/pointing_game_ebp_voc07_difficult.txt
torchray/benchmark/server.py