Metadata-Version: 2.1
Name: torchray
Version: 1.0.0.2
Summary: TorchRay is a PyTorch library of visualization methods for convnets.
Home-page: https://github.com/facebookresearch/TorchRay
Author: Andrea Vedaldi
Author-email: vedaldi@fb.com
License: Creative Commons Attribution-Noncommercial 4.0 International
Download-URL: https://github.com/ruthcfong/TorchRay/archive/v1.0.0.2.tar.gz
Platform: UNKNOWN
Classifier: Development Status :: 5 - Production/Stable
Classifier: Intended Audience :: Developers
Classifier: Programming Language :: Python :: 3
Classifier: Programming Language :: Python :: 3.6
Classifier: Programming Language :: Python :: 3.7
Classifier: Topic :: Scientific/Engineering
Classifier: Topic :: Scientific/Engineering :: Artificial Intelligence
Classifier: Topic :: Software Development
Classifier: Topic :: Software Development :: Libraries
Classifier: Topic :: Software Development :: Libraries :: Python Modules
Requires-Python: >=3.6
